escondite/__init__.py
escondite/_cache.py
escondite-0.1.1.dist-info/WHEEL
escondite-0.1.1.dist-info/METADATA
escondite-0.1.1.dist-info/RECORD
