Metadata-Version: 2.3
Name: escondite
Version: 0.1.1
Summary: Store objects in caches at startup time.
Requires-Python: >=3.13
